{
  "count": 11,
  "listing": "",
  "posts": [
    {
      "err": "fetch failed",
      "id": "t3_eag8vv"
    },
    {
      "err": "fetch failed",
      "id": "t3_e8zr1s"
    },
    {
      "err": "fetch failed",
      "id": "t3_e7n8ge"
    },
    {
      "err": "fetch failed",
      "id": "t3_e7ill8"
    },
    {
      "err": "fetch failed",
      "id": "t3_e7f6fv"
    },
    {
      "err": "fetch failed",
      "id": "t3_e7ew81"
    },
    {
      "err": "fetch failed",
      "id": "t3_e7ecfu"
    },
    {
      "err": "fetch failed",
      "id": "t3_e7g3up"
    },
    {
      "err": "fetch failed",
      "id": "t3_e7emki"
    },
    {
      "err": "fetch failed",
      "id": "t3_e5k50q"
    },
    {
      "err": "Too many consecutive failures (10). Terminating.",
      "id": "TERMINATED"
    }
  ]
}